xarray_ome_ngff/__about__.py
xarray_ome_ngff/__init__.py
xarray_ome_ngff/array_wrap.py
xarray_ome_ngff/core.py
xarray_ome_ngff/py.typed
xarray_ome_ngff/v04/__init__.py
xarray_ome_ngff/v04/multiscale.py
xarray_ome_ngff-3.1.1.dist-info/METADATA
xarray_ome_ngff-3.1.1.dist-info/WHEEL
xarray_ome_ngff-3.1.1.dist-info/licenses/LICENSE.md
xarray_ome_ngff-3.1.1.dist-info/RECORD
