Metadata-Version: 2.3
Name: xarray-ome-ngff
Version: 3.1.1
Summary: Xarray and OME-NGFF
Project-URL: Documentation, https://janeliascicomp.github.io/xarray-ome-ngff
Project-URL: Issues, https://github.com/janeliascicomp/xarray-ome-ngff/issues
Project-URL: Source, https://github.com/janeliascicomp/xarray-ome-ngff
Author-email: Davis Vann Bennett <davis.v.bennett@gmail.com>
License-Expression: MIT
License-File: LICENSE.md
Keywords: ngff,xarray
Classifier: Development Status :: 4 - Beta
Classifier: Programming Language :: Python
Classifier: Programming Language :: Python :: 3.10
Classifier: Programming Language :: Python :: 3.11
Classifier: Programming Language :: Python :: 3.12
Classifier: Programming Language :: Python :: Implementation :: CPython
Requires-Python: >=3.9
Requires-Dist: dask>=2022.3.0
Requires-Dist: pint>=0.24
Requires-Dist: pydantic-ome-ngff==0.6.0
Requires-Dist: pydantic<3,>=2.0.0
Requires-Dist: xarray>=2023.2.0
Requires-Dist: zarr<3.0.0
